superbrowserapi/__init__.py
superbrowserapi/_code.py
superbrowserapi/utils.py
yz_utils/__init__.py
yz_utils/consumer.py
yz_utils/web_api.py
yz_rpa_utils-0.2.6.dist-info/METADATA
yz_rpa_utils-0.2.6.dist-info/WHEEL
yz_rpa_utils-0.2.6.dist-info/top_level.txt
yz_rpa_utils-0.2.6.dist-info/RECORD
