Metadata-Version: 2.1
Name: yz-rpa-utils
Version: 0.2.6
Summary: 整合紫鸟操作店铺API
Home-page: https://github.com/lzzkey
Author: lzzkey
Author-email: 617692766@qq.com
Classifier: Programming Language :: Python :: 3.7
Classifier: License :: OSI Approved :: MIT License
Classifier: Operating System :: OS Independent
Requires-Python: >=3.7
Requires-Dist: requests
Requires-Dist: uuid
Requires-Dist: nanoid
Requires-Dist: psutil
Requires-Dist: pretty-errors
Requires-Dist: selenium
Requires-Dist: retrying
Requires-Dist: pywin32
Requires-Dist: PyExecJS
Requires-Dist: aiohttp
Requires-Dist: tenacity
Requires-Dist: asyncio
